MANIFEST.in
README.md
requirements.txt
setup.py
django_dialogflow/__init__.py
django_dialogflow/manage.py
django_dialogflow.egg-info/PKG-INFO
django_dialogflow.egg-info/SOURCES.txt
django_dialogflow.egg-info/dependency_links.txt
django_dialogflow.egg-info/requires.txt
django_dialogflow.egg-info/top_level.txt
django_dialogflow.egg-info/zip-safe