Metadata-Version: 1.1
Name: django-dialogflow
Version: 0.0.4
Summary: Django Dialogflow chat agent
Home-page: https://github.com/vkosuri/django-dialogflow
Author: Mallikarjunarao Kosuri
Author-email: malli.kv2@gmail.com
License: BSD
Download-URL: https://github.com/vkosuri/django-dialogflow/tarball/0.0.4
Keywords: Django,Dialogflow,api.ai,chat,bot
Platform: any
Classifier: Development Status :: 4 - Beta
Classifier: Intended Audience :: Developers
Classifier: License :: OSI Approved :: MIT License
Classifier: Environment :: Console
Classifier: Environment :: Web Environment
Classifier: Operating System :: OS Independent
Classifier: Topic :: Software Development :: Libraries :: Python Modules
Classifier: Topic :: Communications :: Chat
Classifier: Topic :: Internet
Classifier: Programming Language :: Python
Classifier: Programming Language :: Python :: 2.7
Classifier: Programming Language :: Python :: 3
Classifier: Programming Language :: Python :: 3.4
Classifier: Programming Language :: Python :: 3.5
